wistx_mcp/__init__.py
wistx_mcp/config.py
wistx_mcp/server.py
wistx_mcp/docs/ANTIGRAVITY_SETUP.md
wistx_mcp/docs/DISTRIBUTED_RATE_LIMITING.md
wistx_mcp/docs/DISTRIBUTED_STORAGE_VALIDATION.md
wistx_mcp/docs/LOCAL_DEVELOPMENT.md
wistx_mcp/models/__init__.py
wistx_mcp/models/cloud_discovery.py
wistx_mcp/models/incident.py
wistx_mcp/models/package_health.py
wistx_mcp/models/quality_score.py
wistx_mcp/models/report_template.py
wistx_mcp/models/template.py
wistx_mcp/models/template_rating.py
wistx_mcp/models/template_storage.py
wistx_mcp/services/__init__.py
wistx_mcp/services/health_check.py
wistx_mcp/services/pattern_discovery_service.py
wistx_mcp/services/pattern_quality_assurance.py
wistx_mcp/services/pattern_quality_scorer.py
wistx_mcp/services/pattern_validation_service.py
wistx_mcp/services/quality_scorer.py
wistx_mcp/services/repository_discovery.py
wistx_mcp/services/repository_forking.py
wistx_mcp/services/template_curation.py
wistx_mcp/services/template_discovery.py
wistx_mcp/services/template_standardization.py
wistx_mcp/services/template_storage_service.py
wistx_mcp/services/template_validation.py
wistx_mcp/tools/__init__.py
wistx_mcp/tools/best_practices.py
wistx_mcp/tools/code_examples.py
wistx_mcp/tools/compliance.py
wistx_mcp/tools/design_architecture.py
wistx_mcp/tools/discover_cloud_resources.py
wistx_mcp/tools/generate_documentation.py
wistx_mcp/tools/get_github_file_tree.py
wistx_mcp/tools/infrastructure_context.py
wistx_mcp/tools/intelligent_context.py
wistx_mcp/tools/manage_infrastructure.py
wistx_mcp/tools/manage_infrastructure_lifecycle.py
wistx_mcp/tools/manage_integration.py
wistx_mcp/tools/mcp_tools.py
wistx_mcp/tools/package_search.py
wistx_mcp/tools/pricing.py
wistx_mcp/tools/regex_search.py
wistx_mcp/tools/resolve_incident.py
wistx_mcp/tools/search_codebase.py
wistx_mcp/tools/troubleshoot_issue.py
wistx_mcp/tools/unified_code_search.py
wistx_mcp/tools/unified_compliance_automation.py
wistx_mcp/tools/unified_context.py
wistx_mcp-1.0.71.dist-info/METADATA
wistx_mcp-1.0.71.dist-info/WHEEL
wistx_mcp-1.0.71.dist-info/entry_points.txt
wistx_mcp-1.0.71.dist-info/RECORD
